odoo/addons/document_page_project/README.rst
odoo/addons/document_page_project/__init__.py
odoo/addons/document_page_project/__manifest__.py
odoo/addons/document_page_project/i18n/document_page_project.pot
odoo/addons/document_page_project/models/__init__.py
odoo/addons/document_page_project/models/document_page.py
odoo/addons/document_page_project/models/project_project.py
odoo/addons/document_page_project/readme/CONTRIBUTORS.rst
odoo/addons/document_page_project/readme/DESCRIPTION.rst
odoo/addons/document_page_project/readme/USAGE.rst
odoo/addons/document_page_project/static/description/icon.png
odoo/addons/document_page_project/static/description/index.html
odoo/addons/document_page_project/views/document_page_views.xml
odoo/addons/document_page_project/views/project_project_views.xml
odoo11_addon_document_page_project-11.0.1.0.0.99.dev6.dist-info/METADATA
odoo11_addon_document_page_project-11.0.1.0.0.99.dev6.dist-info/WHEEL
odoo11_addon_document_page_project-11.0.1.0.0.99.dev6.dist-info/top_level.txt
odoo11_addon_document_page_project-11.0.1.0.0.99.dev6.dist-info/RECORD
